Sallust/Constants.py
Sallust/TestCase.py
Sallust/__init__.py
Sallust/__main__.py
Sallust/GUI/ColorizeFunctions.py
Sallust/GUI/DataTable.py
Sallust/GUI/Editor.py
Sallust/GUI/Graphics.py
Sallust/GUI/MainWindow.py
Sallust/GUI/PageXML.py
Sallust/GUI/PopUpWindow.py
Sallust/GUI/Steps.py
Sallust/GUI/__init__.py
Sallust/GUI/GraphicsWidgets/StepsTable.py
Sallust/GUI/GraphicsWidgets/TestCaseTable.py
Sallust/Tools/ExecuteMethods.py
Sallust/Tools/LoadXML.py
Sallust/Tools/ResultsPDF.py
Sallust/Tools/TestData.py
sallust-0.15.13.dist-info/LICENSE
sallust-0.15.13.dist-info/METADATA
sallust-0.15.13.dist-info/WHEEL
sallust-0.15.13.dist-info/top_level.txt
sallust-0.15.13.dist-info/RECORD
