Metadata-Version: 2.1
Name: sallust
Version: 0.15.13
Summary: sallust is a modern, open source testing support application. it helps track tests cases
Home-page: https://github.com/socisomer/Sallust
Author: Joan Albert Espinosa
Author-email: joanalbert.espinosa@gmail.com
License: GNU General Public License v3.0
Platform: UNKNOWN
Requires-Dist: lxml
Requires-Dist: matplotlib
Requires-Dist: Pillow
Requires-Dist: numpy
Requires-Dist: natsort
Requires-Dist: fpdf
